gotoshare/__init__.py
gotoshare-1.0.1.dist-info/licenses/LICENSE
gotoshare-1.0.1.dist-info/METADATA
gotoshare-1.0.1.dist-info/WHEEL
gotoshare-1.0.1.dist-info/top_level.txt
gotoshare-1.0.1.dist-info/RECORD
