Metadata-Version: 2.4
Name: gotoshare
Version: 1.0.1
Summary: GotoShare SDK - A股数据自托管服务客户端，与tushare接口兼容
Home-page: https://github.com/gotoshare/gotoshare
Author: GotoShare
Author-email: GotoShare <gotoshare@example.com>
License: MIT
Project-URL: Homepage, https://github.com/gotoshare/gotoshare
Keywords: stock,finance,tushare,A股,量化
Classifier: Development Status :: 4 - Beta
Classifier: Intended Audience :: Developers
Classifier: Intended Audience :: Financial and Insurance Industry
Classifier: License :: OSI Approved :: MIT License
Classifier: Programming Language :: Python :: 3
Classifier: Programming Language :: Python :: 3.8
Classifier: Programming Language :: Python :: 3.9
Classifier: Programming Language :: Python :: 3.10
Classifier: Programming Language :: Python :: 3.11
Classifier: Programming Language :: Python :: 3.12
Requires-Python: >=3.8
License-File: LICENSE
Requires-Dist: httpx>=0.24.0
Requires-Dist: pandas>=1.5.0
Dynamic: author
Dynamic: home-page
Dynamic: license-file
Dynamic: requires-python
